<?xml version="1.0" encoding="utf-8"?>
<EntityRelationships>
  <EntityRelationship Name="team_accounts">
    <EntityRelationshipType>OneToMany</EntityRelationshipType>
    <IntroducedVersion>5.0.0.0</IntroducedVersion>
    <IsHierarchical>0</IsHierarchical>
    <ReferencingEntityName>Account</ReferencingEntityName>
    <ReferencedEntityName>Team</ReferencedEntityName>
    <CascadeAssign>NoCascade</CascadeAssign>
    <CascadeDelete>NoCascade</CascadeDelete>
    <CascadeReparent>NoCascade</CascadeReparent>
    <CascadeShare>NoCascade</CascadeShare>
    <CascadeUnshare>NoCascade</CascadeUnshare>
    <CascadeRollupView>NoCascade</CascadeRollupView>
    <ReferencingAttributeName>OwningTeam</ReferencingAttributeName>
    <RelationshipDescription>
      <Descriptions>
        <Description description="Unique identifier of the team who owns the account." languagecode="1033" />
      </Descriptions>
    </RelationshipDescription>
  </EntityRelationship>
  <EntityRelationship Name="team_facs_application">
    <EntityRelationshipType>OneToMany</EntityRelationshipType>
    <IsCustomizable>1</IsCustomizable>
    <IntroducedVersion>1.0.0</IntroducedVersion>
    <IsHierarchical>0</IsHierarchical>
    <ReferencingEntityName>facs_application</ReferencingEntityName>
    <ReferencedEntityName>Team</ReferencedEntityName>
    <CascadeAssign>NoCascade</CascadeAssign>
    <CascadeDelete>NoCascade</CascadeDelete>
    <CascadeReparent>NoCascade</CascadeReparent>
    <CascadeShare>NoCascade</CascadeShare>
    <CascadeUnshare>NoCascade</CascadeUnshare>
    <ReferencingAttributeName>OwningTeam</ReferencingAttributeName>
    <RelationshipDescription>
      <Descriptions>
        <Description description="Unique identifier for the team that owns the record." languagecode="1033" />
      </Descriptions>
    </RelationshipDescription>
  </EntityRelationship>
  <EntityRelationship Name="team_facs_court">
    <EntityRelationshipType>OneToMany</EntityRelationshipType>
    <IsCustomizable>1</IsCustomizable>
    <IntroducedVersion>1.0.0</IntroducedVersion>
    <IsHierarchical>0</IsHierarchical>
    <ReferencingEntityName>facs_court</ReferencingEntityName>
    <ReferencedEntityName>Team</ReferencedEntityName>
    <CascadeAssign>NoCascade</CascadeAssign>
    <CascadeDelete>NoCascade</CascadeDelete>
    <CascadeReparent>NoCascade</CascadeReparent>
    <CascadeShare>NoCascade</CascadeShare>
    <CascadeUnshare>NoCascade</CascadeUnshare>
    <ReferencingAttributeName>OwningTeam</ReferencingAttributeName>
    <RelationshipDescription>
      <Descriptions>
        <Description description="Unique identifier for the team that owns the record." languagecode="1033" />
      </Descriptions>
    </RelationshipDescription>
  </EntityRelationship>
  <EntityRelationship Name="team_facs_education">
    <EntityRelationshipType>OneToMany</EntityRelationshipType>
    <IsCustomizable>1</IsCustomizable>
    <IntroducedVersion>1.0.0</IntroducedVersion>
    <IsHierarchical>0</IsHierarchical>
    <ReferencingEntityName>facs_education</ReferencingEntityName>
    <ReferencedEntityName>Team</ReferencedEntityName>
    <CascadeAssign>NoCascade</CascadeAssign>
    <CascadeDelete>NoCascade</CascadeDelete>
    <CascadeReparent>NoCascade</CascadeReparent>
    <CascadeShare>NoCascade</CascadeShare>
    <CascadeUnshare>NoCascade</CascadeUnshare>
    <ReferencingAttributeName>OwningTeam</ReferencingAttributeName>
    <RelationshipDescription>
      <Descriptions>
        <Description description="Unique identifier for the team that owns the record." languagecode="1033" />
      </Descriptions>
    </RelationshipDescription>
  </EntityRelationship>
  <EntityRelationship Name="team_facs_relationship">
    <EntityRelationshipType>OneToMany</EntityRelationshipType>
    <IsCustomizable>1</IsCustomizable>
    <IntroducedVersion>1.0.0</IntroducedVersion>
    <IsHierarchical>0</IsHierarchical>
    <ReferencingEntityName>facs_relationship</ReferencingEntityName>
    <ReferencedEntityName>Team</ReferencedEntityName>
    <CascadeAssign>NoCascade</CascadeAssign>
    <CascadeDelete>NoCascade</CascadeDelete>
    <CascadeReparent>NoCascade</CascadeReparent>
    <CascadeShare>NoCascade</CascadeShare>
    <CascadeUnshare>NoCascade</CascadeUnshare>
    <ReferencingAttributeName>OwningTeam</ReferencingAttributeName>
    <RelationshipDescription>
      <Descriptions>
        <Description description="Unique identifier for the team that owns the record." languagecode="1033" />
      </Descriptions>
    </RelationshipDescription>
  </EntityRelationship>
  <EntityRelationship Name="team_pfedyn_iteration">
    <EntityRelationshipType>OneToMany</EntityRelationshipType>
    <IsCustomizable>1</IsCustomizable>
    <IntroducedVersion>1.0.0.0</IntroducedVersion>
    <IsHierarchical>0</IsHierarchical>
    <ReferencingEntityName>pfedyn_iteration</ReferencingEntityName>
    <ReferencedEntityName>Team</ReferencedEntityName>
    <CascadeAssign>NoCascade</CascadeAssign>
    <CascadeDelete>NoCascade</CascadeDelete>
    <CascadeReparent>NoCascade</CascadeReparent>
    <CascadeShare>NoCascade</CascadeShare>
    <CascadeUnshare>NoCascade</CascadeUnshare>
    <ReferencingAttributeName>OwningTeam</ReferencingAttributeName>
    <RelationshipDescription>
      <Descriptions>
        <Description description="Unique identifier for the team that owns the record." languagecode="1033" />
      </Descriptions>
    </RelationshipDescription>
  </EntityRelationship>
  <EntityRelationship Name="team_pfedyn_project">
    <EntityRelationshipType>OneToMany</EntityRelationshipType>
    <IsCustomizable>1</IsCustomizable>
    <IntroducedVersion>1.0</IntroducedVersion>
    <IsHierarchical>0</IsHierarchical>
    <ReferencingEntityName>pfedyn_project</ReferencingEntityName>
    <ReferencedEntityName>Team</ReferencedEntityName>
    <CascadeAssign>NoCascade</CascadeAssign>
    <CascadeDelete>NoCascade</CascadeDelete>
    <CascadeReparent>NoCascade</CascadeReparent>
    <CascadeShare>NoCascade</CascadeShare>
    <CascadeUnshare>NoCascade</CascadeUnshare>
    <ReferencingAttributeName>OwningTeam</ReferencingAttributeName>
    <RelationshipDescription>
      <Descriptions>
        <Description description="Unique identifier for the team that owns the record." languagecode="1033" />
      </Descriptions>
    </RelationshipDescription>
  </EntityRelationship>
  <EntityRelationship Name="team_pfedyn_workitem">
    <EntityRelationshipType>OneToMany</EntityRelationshipType>
    <IsCustomizable>1</IsCustomizable>
    <IntroducedVersion>1.0</IntroducedVersion>
    <IsHierarchical>0</IsHierarchical>
    <ReferencingEntityName>pfedyn_workitem</ReferencingEntityName>
    <ReferencedEntityName>Team</ReferencedEntityName>
    <CascadeAssign>NoCascade</CascadeAssign>
    <CascadeDelete>NoCascade</CascadeDelete>
    <CascadeReparent>NoCascade</CascadeReparent>
    <CascadeShare>NoCascade</CascadeShare>
    <CascadeUnshare>NoCascade</CascadeUnshare>
    <ReferencingAttributeName>OwningTeam</ReferencingAttributeName>
    <RelationshipDescription>
      <Descriptions>
        <Description description="Unique identifier for the team that owns the record." languagecode="1033" />
      </Descriptions>
    </RelationshipDescription>
  </EntityRelationship>
</EntityRelationships>